examenes/segundo-parcial/examen-practico/flipflopSR.vhdl
library IEEE;
use IEEE.std_logic_1164.all;

entity flipFlopSR is
    port (
        status, notStatus : out std_logic;
        clock, s, r : in std_logic
    );
end entity;

architecture arch_flipFlopSR of flipFlopSR is

    signal internalQ : std_logic;
    signal internalSR : std_logic_vector (1 downto 0);

begin

    status <= internalQ;
    notStatus <= not internalQ;

    main_process : process (clock)
    begin

        internalSR <= s & r;
        if rising_edge (clock) then
            report "Procesando tic tac.. clock=" & std_logic'image(clock);
            report "    s=" & std_logic'image(s);
            report "    r=" & std_logic'image(r);

            if internalSR = "00" then
                --internalQ <= internalQ;
            elsif internalSR = "01" then
                internalQ <= '0';
            elsif internalSR = "10" then
                internalQ <= '1';
            else -- internalSR is "11"
                -- Esto no está permitido, queda en estado inestable.
                internalQ <= 'Z';
            end if;
        end if;

    end process;

end architecture;

examenes/segundo-parcial/examen-practico/flipflopSR_tb.vhdl
library IEEE;
use IEEE.std_logic_1164.all;

entity flipFlopSR_tb is
end entity;

architecture arch_flipFlopSR_tb of flipFlopSR_tb is

    component flipFlopSR is
        port (
            status, notStatus : out std_logic;
            clock, s, r : in std_logic
        );
    end component;

    signal testStatus, testNotStatus, testS, testR : std_logic;
    signal testClock : std_logic := '0';
    signal tics : integer := 0;

begin

    testing_unit: flipFlopSR port map (
        status => testStatus,
        notStatus => testNotStatus,
        clock => testClock,
        s => testS,
        r => testR
    );

    generate_100Mhzs_clock : process
    begin

        report "Tic tac.. testClock=" & std_logic'image(testClock);
        testClock <= not testClock;

        if testClock = '1' then tics <= tics + 1; end if;
        if tics >= 20 then wait; end if;

        wait for 5 ns; -- Tiempo de espera en un flanco de reloj.

    end process;

    main_process : process
    begin

        wait for 15 ns;

        -- Reset inicial
        testS <= '0'; testR <= '1'; wait for 20 ns;

        testS <= '0'; testR <= '0'; wait for 20 ns;
        testS <= '0'; testR <= '1'; wait for 20 ns;
        testS <= '1'; testR <= '0'; wait for 20 ns;
        --testS <= '1'; testR <= '1'; wait for 20 ns;

        testS <= '0'; testR <= '0'; wait for 20 ns;
        testS <= '0'; testR <= '1'; wait for 20 ns;
        testS <= '1'; testR <= '0'; wait for 20 ns;
        --testS <= '1'; testR <= '1'; wait for 20 ns;

        testS <= '0'; testR <= '0'; wait for 20 ns;
        testS <= '0'; testR <= '1'; wait for 20 ns;
        testS <= '1'; testR <= '0'; wait for 20 ns;
        --testS <= '1'; testR <= '1'; wait for 20 ns;
        wait;

    end process;

end architecture;

examenes/segundo-parcial/examen-practico/test.vcd
$date
  Wed Dec  1 19:17:11 2021
$end
$version
  GHDL v0
$end
$timescale
  1 fs
$end
$scope module standard $end
$upscope $end
$scope module std_logic_1164 $end
$upscope $end
$scope module flipflopsr_tb $end
$var reg 1 ! teststatus $end
$var reg 1 " testnotstatus $end
$var reg 1 # tests $end
$var reg 1 $ testr $end
$var reg 1 % testclock $end
$var integer 32 & tics $end
$scope module testing_unit $end
$var reg 1 ' status $end
$var reg 1 ( notstatus $end
$var reg 1 ) clock $end
$var reg 1 * s $end
$var reg 1 + r $end
$var reg 1 , internalq $end
$var reg 2 - internalsr[1:0] $end
$upscope $end
$upscope $end
$enddefinitions $end
#0
Z!
X"
U#
U$
1%
b0 &
Z'
X(
1)
U*
U+
Z,
bUU -
#5000000
0%
b1 &
0)
#10000000
1%
1)
#15000000
0#
1$
0%
b10 &
0)
0*
1+
b01 -
#20000000
0!
1"
1%
0'
1(
1)
0,
#25000000
0%
b11 &
0)
#30000000
1%
1)
#35000000
0$
0%
b100 &
0)
0+
b00 -
#40000000
1%
1)
#45000000
0%
b101 &
0)
#50000000
1%
1)
#55000000
1$
0%
b110 &
0)
1+
b01 -
#60000000
1%
1)
#65000000
0%
b111 &
0)
#70000000
1%
1)
#75000000
1#
0$
0%
b1000 &
0)
1*
0+
b10 -
#80000000
1!
0"
1%
1'
0(
1)
1,
#85000000
0%
b1001 &
0)
#90000000
1%
1)
#95000000
0#
0%
b1010 &
0)
0*
b00 -
#100000000
1%
1)
#105000000
0%
b1011 &
0)
#110000000
1%
1)
#115000000
1$
0%
b1100 &
0)
1+
b01 -
#120000000
0!
1"
1%
0'
1(
1)
0,
#125000000
0%
b1101 &
0)
#130000000
1%
1)
#135000000
1#
0$
0%
b1110 &
0)
1*
0+
b10 -
#140000000
1!
0"
1%
1'
0(
1)
1,
#145000000
0%
b1111 &
0)
#150000000
1%
1)
#155000000
0#
0%
b10000 &
0)
0*
b00 -
#160000000
1%
1)
#165000000
0%
b10001 &
0)
#170000000
1%
1)
#175000000
1$
0%
b10010 &
0)
1+
b01 -
#180000000
0!
1"
1%
0'
1(
1)
0,
#185000000
0%
b10011 &
0)
#190000000
1%
1)
#195000000
1#
0$
0%
b10100 &
0)
1*
0+
b10 -
#200000000
1!
0"
1%
1'
0(
1)
1,
